python_tuya_oittm/__init__.py
python_tuya_oittm/api_client.py
python_tuya_oittm/device_maps/__init__.py
python_tuya_oittm/device_maps/oittm/__init__.py
python_tuya_oittm/helpers/__init__.py
python_tuya_oittm/helpers/message_parser.py
python_tuya_oittm/security/__init__.py
python_tuya_oittm/security/aescipher.py
python_tuya_oittm/security/cipher.py
python_tuya_oittm-0.0.1.dist-info/METADATA
python_tuya_oittm-0.0.1.dist-info/RECORD
python_tuya_oittm-0.0.1.dist-info/WHEEL
python_tuya_oittm-0.0.1.dist-info/top_level.txt
