Metadata-Version: 2.1
Name: python-tuya-oittm
Version: 0.0.1
Summary: A package for communicating with Tuya/Oittm devices on a local network.
Home-page: https://github.com/Supermortal/python-tuya-oittm
Author: Supermotal
Author-email: supermortaldns@gmail.com
License: UNKNOWN
Platform: UNKNOWN
Classifier: Development Status :: 3 - Alpha
Classifier: Programming Language :: Python :: 3.5
Classifier: Programming Language :: Python :: 3.6
Classifier: Programming Language :: Python :: 3.7
Classifier: Programming Language :: Python :: 3 :: Only
Classifier: License :: OSI Approved :: MIT License
Classifier: Operating System :: OS Independent
Requires-Dist: pycryptodome
